LinkedList/__init__.py
LinkedList/__main__.py
LinkedList/linkedlist.py
Advance_LinkedList-1.0.2.dist-info/LICENSE
Advance_LinkedList-1.0.2.dist-info/METADATA
Advance_LinkedList-1.0.2.dist-info/WHEEL
Advance_LinkedList-1.0.2.dist-info/top_level.txt
Advance_LinkedList-1.0.2.dist-info/RECORD
