Metadata-Version: 2.1
Name: Advance-LinkedList
Version: 1.0.2
Summary: It is LinkedList Data Structure
Home-page: https://github.com/nit22032002/Advance-LinkedList
Author: Nitin
Author-email: nit2203@gmail.com
License: MIT
Platform: UNKNOWN
Classifier: License :: OSI Approved :: MIT License
Classifier: Programming Language :: Python :: 3.6
Classifier: Programming Language :: Python :: 3.7
Classifier: Programming Language :: Python :: 3.8
License-File: LICENSE
